ardilla/__init__.py
ardilla/abc.py
ardilla/crud.py
ardilla/engine.py
ardilla/errors.py
ardilla/fields.py
ardilla/logging.py
ardilla/migration.py
ardilla/models.py
ardilla/ordering.py
ardilla/queries.py
ardilla/schemas.py
ardilla/asyncio/__init__.py
ardilla/asyncio/crud.py
ardilla/asyncio/engine.py
ardilla-0.4.0b0.dist-info/LICENCE
ardilla-0.4.0b0.dist-info/METADATA
ardilla-0.4.0b0.dist-info/WHEEL
ardilla-0.4.0b0.dist-info/top_level.txt
ardilla-0.4.0b0.dist-info/RECORD
